lamatrix/__init__.py
lamatrix/bounded.py
lamatrix/combine.py
lamatrix/distributions.py
lamatrix/io.py
lamatrix/math.py
lamatrix/model.py
lamatrix/models/astrophysical.py
lamatrix/models/gaussian.py
lamatrix/models/simple.py
lamatrix/models/sip.py
lamatrix/models/spline.py
lamatrix-1.0.1.dist-info/LICENSE
lamatrix-1.0.1.dist-info/METADATA
lamatrix-1.0.1.dist-info/WHEEL
lamatrix-1.0.1.dist-info/RECORD
