Metadata-Version: 2.3
Name: lamatrix
Version: 1.0.1
Summary: 
Author: Christina Hedges
Author-email: christina.l.hedges@nasa.gov
Requires-Python: >=3.9,<4.0
Classifier: Programming Language :: Python :: 3
Classifier: Programming Language :: Python :: 3.9
Classifier: Programming Language :: Python :: 3.10
Classifier: Programming Language :: Python :: 3.11
Classifier: Programming Language :: Python :: 3.12
Classifier: Programming Language :: Python :: 3.13
Provides-Extra: ffi
Requires-Dist: astropy (>=5.0.0) ; extra == "ffi"
Requires-Dist: lkspacecraft (>=1.0.5) ; extra == "ffi"
Requires-Dist: numpy (>=1.26.4,<2.0.0)
Requires-Dist: rich (>=13.7.1,<14.0.0)
Requires-Dist: scipy (>=1.3)
Requires-Dist: sparse3d (>1.0.0) ; extra == "ffi"
